LICENSE.txt
MANIFEST.in
README.rst
requirements.txt
setup.py
test-requirements.txt
opsgenie/__init__.py
opsgenie/client.py
opsgenie/config.py
opsgenie/errors.py
opsgenie/request.py
opsgenie/response.py
opsgenie/service.py
opsgenie/utility.py
opsgenie/alert/__init__.py
opsgenie/alert/requests.py
opsgenie/alert/responses.py
opsgenie/alert/service.py
opsgenie/swagger_client/__init__.py
opsgenie/swagger_client/api_client.py
opsgenie/swagger_client/configuration.py
opsgenie/swagger_client/rest.py
opsgenie/swagger_client/apis/__init__.py
opsgenie/swagger_client/apis/alert_api.py
opsgenie/swagger_client/models/__init__.py
opsgenie/swagger_client/models/acknowledge_alert_request.py
opsgenie/swagger_client/models/add_alert_details_request.py
opsgenie/swagger_client/models/add_alert_note_request.py
opsgenie/swagger_client/models/add_alert_tags_request.py
opsgenie/swagger_client/models/add_alert_team_request.py
opsgenie/swagger_client/models/add_saved_search_request.py
opsgenie/swagger_client/models/add_saved_search_response.py
opsgenie/swagger_client/models/alert.py
opsgenie/swagger_client/models/alert_action_request.py
opsgenie/swagger_client/models/alert_integration.py
opsgenie/swagger_client/models/alert_log.py
opsgenie/swagger_client/models/alert_note.py
opsgenie/swagger_client/models/alert_recipient.py
opsgenie/swagger_client/models/alert_report.py
opsgenie/swagger_client/models/alert_request_status.py
opsgenie/swagger_client/models/all_recipient.py
opsgenie/swagger_client/models/assign_alert_request.py
opsgenie/swagger_client/models/base_alert.py
opsgenie/swagger_client/models/base_response.py
opsgenie/swagger_client/models/close_alert_request.py
opsgenie/swagger_client/models/create_alert_request.py
opsgenie/swagger_client/models/delete_alert_details_request.py
opsgenie/swagger_client/models/delete_alert_request.py
opsgenie/swagger_client/models/delete_alert_tags_request.py
opsgenie/swagger_client/models/error_response.py
opsgenie_sdk_criteo.egg-info/PKG-INFO
opsgenie_sdk_criteo.egg-info/SOURCES.txt
opsgenie_sdk_criteo.egg-info/dependency_links.txt
opsgenie_sdk_criteo.egg-info/requires.txt
opsgenie_sdk_criteo.egg-info/top_level.txt
