Metadata-Version: 1.0
Name: opsgenie-sdk-criteo
Version: 0.3.1
Summary: Python SDK for OpsGenie Web/REST API (Criteo Forks)
Home-page: https://github.com/opsgenie/opsgenie-python-sdk
Author: OpsGenie
Author-email: support@opsgenie.com
License: Apache License 2.0
Keywords: OpsGenie,Web Api,Rest Api,Alert Api,Swagger
Platform: UNKNOWN
